{"is_source_file": true, "format": "JavaScript module (.mjs)", "description": "ESLint configuration file for JavaScript and React projects, specifying parser options, environment globals, and plugin configurations.", "external_files": ["@eslint/js", "eslint-plugin-react"], "external_methods": [], "published": [], "classes": [], "methods": [], "calls": ["pluginJs", "pluginReact", "pluginJs.configs.recommended"], "search-terms": ["eslint", "plugin-js", "plugin-react", "jsm", "eslint-plugin-react", "parserOptions", "rules", "globals", "jsx"], "state": 2, "file_id": 1, "knowledge_revision": 18, "git_revision": "d2119a0054b366500252d1d7cf021be369fcc287", "hash": "be6538e7523bc2e9da0743133d784136", "format-version": 4, "code-base-name": "bug_detector_frontend", "filename": "bug_detector_frontend/eslint.config.mjs", "revision_history": [{"18": "d2119a0054b366500252d1d7cf021be369fcc287"}]}